GraphAtoms/__init__.py
GraphAtoms/common/__init__.py
GraphAtoms/common/_abc.py
GraphAtoms/common/base.py
GraphAtoms/common/error.py
GraphAtoms/containner/__init__.py
GraphAtoms/containner/_aMixin.py
GraphAtoms/containner/_aOther.py
GraphAtoms/containner/_atomic.py
GraphAtoms/containner/_g2DataPyG.py
GraphAtoms/containner/_g2IGraph.py
GraphAtoms/containner/_g2NetworkX.py
GraphAtoms/containner/_g2RustworkX.py
GraphAtoms/containner/_gBonded.py
GraphAtoms/containner/_graph.py
GraphAtoms/containner/_sysCluster.py
GraphAtoms/containner/_sysGas.py
GraphAtoms/containner/_system.py
GraphAtoms/reaction/__init__.py
GraphAtoms/reaction/_dtSQL.py
GraphAtoms/reaction/_event.py
GraphAtoms/utils/__init__.py
GraphAtoms/utils/_pyarrow.py
GraphAtoms/utils/bytes.py
GraphAtoms/utils/geometry.py
GraphAtoms/utils/ndarray.py
GraphAtoms/utils/rdtool.py
GraphAtoms/utils/rotation.py
GraphAtoms/utils/string.py
graphatoms-1.0.0.dist-info/licenses/LICENSE
graphatoms-1.0.0.dist-info/METADATA
graphatoms-1.0.0.dist-info/WHEEL
graphatoms-1.0.0.dist-info/top_level.txt
graphatoms-1.0.0.dist-info/RECORD
