Metadata-Version: 2.4
Name: GraphAtoms
Version: 1.0.0
Summary: The Chemical Core Class for Graph Theory Analysis & Graph Neural Network.
Author-email: LiuGaoyong <liugaoyong_88@163.com>
Requires-Python: >=3.10
License-File: LICENSE
Requires-Dist: ase
Requires-Dist: pymatgen>2023.6
Requires-Dist: rdkit>=2025
Requires-Dist: dscribe>=2.1
Requires-Dist: vesin
Requires-Dist: numba>=0.61
Requires-Dist: numpy>=2.0
Requires-Dist: pandas
Requires-Dist: scipy
Requires-Dist: torch
Requires-Dist: scikit-learn>=1.5
Requires-Dist: sparse
Requires-Dist: torch_geometric
Requires-Dist: igraph>=0.11
Requires-Dist: networkx>=3.3
Requires-Dist: rustworkx>=0.16
Requires-Dist: numpydantic
Requires-Dist: pydantic>=2.11
Requires-Dist: pydantic-to-pyarrow>=0.1.6
Requires-Dist: python-snappy>=0.7.3
Requires-Dist: pyyaml
Requires-Dist: sqlmodel
Requires-Dist: tomli-w
Requires-Dist: tomli; python_version < "3.11"
Requires-Dist: typing-extensions
Requires-Dist: chardet>=5.2.0
Dynamic: license-file
